Combinational_Circuits/1-to_2_De_Multiplexer/one_to_two_demux.v
module one_to_two_demux(
input sel,
input din,
output dout0,dout1);
assign dout0 = (sel==1'b0)?din:1'b0;
assign dout1 = (sel==1'b1)?din:1'b0;
endmodule

Combinational_Circuits/1-to_4_De_Multiplexer/one_to_four_demux.v
`include "one_to_two_demux.v"
module one_to_four_demux(
input din,
input [1:0]sel,
output out0,out1,out2,out3);

wire w1,w2;
one_to_two_demux m1(sel[0],din,w1,w2);
one_to_two_demux m2(sel[1],w1,out0,out1);
one_to_two_demux m3(sel[1],w2,out2,out3);

endmodule

Combinational_Circuits/1-to_4_De_Multiplexer/one_to_four_demux_testbench.v
`include "one_to_four_demux.v"
module one_to_four_demux_testbench();
  reg [1:0]sel;
  reg din;
  wire out0,out1,out2,out3;
  
  one_to_four_demux dut(din,sel,out0,out1,out2,out3);
  
  initial begin
  $dumpfile("one_to_four_demultiplexer.vcd");
  $dumpvars(0,one_to_four_demux_testbench);  
  end

  initial begin
    $monitor("sel0 = %b, sel1 = %b, din = %b ,  y0 = %0b, y1 = %0b ,y2 = %0b, y3 = %0b", sel[0], sel[1], din, out0,out1,out2,out3);
    sel[0]=0; sel[1]=0; din=0; #10;
    sel[0]=0; sel[1]=0; din=1; #10;
    sel[0]=0; sel[1]=1; din=0; #10;
    sel[0]=0; sel[1]=1; din=1; #10;
    sel[0]=1; sel[1]=0; din=0; #10;
    sel[0]=1; sel[1]=0; din=1; #10;
    sel[0]=1; sel[1]=1; din=0; #10;
    sel[0]=1; sel[1]=1; din=1; #10;
  end
endmodule

Combinational_Circuits/1-to_4_De_Multiplexer/one_to_four_demultiplexer.vcd
$date
	Mon Apr 01 13:12:04 2024
$end
$version
	Icarus Verilog
$end
$timescale
	1s
$end
$scope module one_to_four_demux_testbench $end
$var wire 1 ! out3 $end
$var wire 1 " out2 $end
$var wire 1 # out1 $end
$var wire 1 $ out0 $end
$var reg 1 % din $end
$var reg 2 & sel [1:0] $end
$scope module dut $end
$var wire 1 % din $end
$var wire 2 ' sel [1:0] $end
$var wire 1 ( w2 $end
$var wire 1 ) w1 $end
$var wire 1 ! out3 $end
$var wire 1 " out2 $end
$var wire 1 # out1 $end
$var wire 1 $ out0 $end
$scope module m1 $end
$var wire 1 % din $end
$var wire 1 * sel $end
$var wire 1 ( dout1 $end
$var wire 1 ) dout0 $end
$upscope $end
$scope module m2 $end
$var wire 1 ) din $end
$var wire 1 + sel $end
$var wire 1 # dout1 $end
$var wire 1 $ dout0 $end
$upscope $end
$scope module m3 $end
$var wire 1 ( din $end
$var wire 1 , sel $end
$var wire 1 ! dout1 $end
$var wire 1 " dout0 $end
$upscope $end
$upscope $end
$upscope $end
$enddefinitions $end
#0
$dumpvars
0,
0+
0*
0)
0(
b0 '
b0 &
0%
0$
0#
0"
0!
$end
#10
1$
1)
1%
#20
0$
0)
1+
1,
0%
b10 &
b10 '
#30
1#
1)
1%
#40
0#
0)
0+
0,
1*
0%
b1 &
b1 '
#50
1"
1(
1%
#60
0"
0(
1+
1,
0%
b11 &
b11 '
#70
1!
1(
1%
