Sequential Circuits/D_FlipFlop/d_flip_flop.v
module d_ff(d,clk,rst,q);
input d;
input clk;
input rst;
output reg q;
always @(posedge clk) begin
   if(rst==1)
        q<=0;
    else 
        q<=d;    
end
endmodule

Sequential Circuits/D_FlipFlop/d_flip_flop_testbench.v
`include "d_flip_flop.v"
module d_ff_testbench();
reg d;
reg clk=0;
reg rst;
wire q;

always #10 clk = ~clk;  

d_ff dut(d,clk,rst,q);


initial begin
$dumpfile("d_flip_flop.vcd");
$dumpvars(0,d_ff_testbench);
end


initial begin 
 rst=1;
 #100;
 rst=0;
 d <= 1;
 #100;
 d <= 0;
 #100;
 d <= 1;
 #100
 rst=0;
 $finish();
end 
endmodule

Sequential Circuits/D_FlipFlop/d_flip_flop.vcd
$date
	Mon Apr 08 21:30:35 2024
$end
$version
	Icarus Verilog
$end
$timescale
	1s
$end
$scope module d_ff_testbench $end
$var wire 1 ! q $end
$var reg 1 " clk $end
$var reg 1 # d $end
$var reg 1 $ rst $end
$scope module dut $end
$var wire 1 " clk $end
$var wire 1 # d $end
$var wire 1 $ rst $end
$var reg 1 ! q $end
$upscope $end
$upscope $end
$enddefinitions $end
#0
$dumpvars
1$
x#
0"
x!
$end
#10
0!
1"
#20
0"
#30
1"
#40
0"
#50
1"
#60
0"
#70
1"
#80
0"
#90
1"
#100
1#
0"
0$
#110
1!
1"
#120
0"
#130
1"
#140
0"
#150
1"
#160
0"
#170
1"
#180
0"
#190
1"
#200
0#
0"
#210
0!
1"
#220
0"
#230
1"
#240
0"
#250
1"
#260
0"
#270
1"
#280
0"
#290
1"
#300
1#
0"
#310
1!
1"
