Combinational_Circuits/8_to_3_priority_encoder/eight_to_three_encoder.v

module eight_to_three_encoder(a,b,c,d,e,f,g,h,x,y,z);
input a,b,c,d,e,f,g,h;
output  x,y,z;

assign x = h | g | f | e ; 
assign y = h | g | d | c ;
assign z = h | f | d | b ;

endmodule

Combinational_Circuits/8_to_3_priority_encoder/eight_to_three_encoder_testbench.v
`include "eight_to_three_encoder.v"
module eight_to_three_encoder_testbench();
reg a,b,c,d,e,f,g,h;
wire x,y,z;

initial begin2
$dumpfile("eight_to_three_encoder_waveform.vcd");
$dumpvars(0,eight_to_three_encoder_testbench);
end 

eight_to_three_encoder dut(a,b,c,d,e,f,g,h,x,y,z);
initial begin 


#000 a=1;b=0;c=0;d=0;e=0;f=0;g=0;h=0;//8
#100 a=0;b=1;c=0;d=0;e=0;f=0;g=0;h=0;//7
#100 a=0;b=0;c=1;d=0;e=0;f=0;g=0;h=0;//6
#100 a=0;b=0;c=0;d=1;e=0;f=0;g=0;h=0;//5
#100 a=0;b=0;c=0;d=0;e=1;f=0;g=0;h=0;//4
#100 a=0;b=0;c=0;d=0;e=0;f=1;g=0;h=0;//3
#100 a=0;b=0;c=0;d=0;e=0;f=0;g=1;h=0;//2
#100 a=0;b=0;c=0;d=0;e=0;f=0;g=0;h=1;//1
#100 a=0;b=0;c=0;d=0;e=0;f=0;g=0;h=0;//0

end

initial begin 
    $monitor($time,"Value of a =%b, b =%b ,c= %b,d=%b, e=%b, f=%b, g=%b, h=%b",a,b,c,d,e,f,g,h);
end


endmodule

Combinational_Circuits/8_to_3_priority_encoder/eight_to_three_encoder_waveform.vcd
$date
	Mon Mar 25 17:29:34 2024
$end
$version
	Icarus Verilog
$end
$timescale
	1s
$end
$scope module eight_to_three_encoder_testbench $end
$var wire 1 ! z $end
$var wire 1 " y $end
$var wire 1 # x $end
$var reg 1 $ a $end
$var reg 1 % b $end
$var reg 1 & c $end
$var reg 1 ' d $end
$var reg 1 ( e $end
$var reg 1 ) f $end
$var reg 1 * g $end
$var reg 1 + h $end
$scope module dut $end
$var wire 1 $ a $end
$var wire 1 % b $end
$var wire 1 & c $end
$var wire 1 ' d $end
$var wire 1 ( e $end
$var wire 1 ) f $end
$var wire 1 * g $end
$var wire 1 + h $end
$var wire 1 # x $end
$var wire 1 " y $end
$var wire 1 ! z $end
$upscope $end
$upscope $end
$enddefinitions $end
#0
$dumpvars
0+
0*
0)
0(
0'
0&
0%
1$
0#
0"
0!
$end
#100
1!
1%
0$
#200
1"
0!
1&
0%
#300
1!
1"
1'
0&
#400
0"
0!
1#
1(
0'
#500
1!
1#
1)
0(
#600
1"
0!
1#
1*
0)
#700
1!
1+
0*
#800
0#
0"
0!
0+
