Combinational_Circuits/8_to_3_encoder/eight_to_three_encoder.v
module eight_to_three_encoder(
input [7:0]din,
output reg[2:0]dout);
always@(din)
    case(din)
        8'b10000000:dout=3'b000;
        8'b01000000:dout=3'b001;
        8'b00100000:dout=3'b010;
        8'b00010000:dout=3'b011;
        8'b00001000:dout=3'b100;
        8'b00000100:dout=3'b101;
        8'b00000010:dout=3'b110;
        8'b00000001:dout=3'b111;
    default: dout[2:0]=3'bzzz;
    endcase
endmodule

Combinational_Circuits/8_to_3_encoder/eight_to_three_encoder_testbench.v
`include "eight_to_three_encoder.v"
module eight_to_three_encoder_testbench();
reg [7:0]din;
wire[2:0]dout;

initial begin
$dumpfile("eight_to_three_encoder_waveform.vcd");
$dumpvars(0,eight_to_three_encoder_testbench);
end 

eight_to_three_encoder dut(din,dout);

initial begin 
#100 din=8'b10000000;//case 8
#100 din=8'b01000000;//case 7
#100 din=8'b00100000;//case 6
#100 din=8'b00010000;//case 5
#100 din=8'b00001000;//case 4
#100 din=8'b00000100;//case 3
#100 din=8'b00000010;//case 2
#100 din=8'b00000001;//case 1
end
initial begin 
$monitor("Time=%t,din=%b,dout=%b",$time,din,dout);
end
initial begin 
#1000 $finish;
end 
endmodule

Combinational_Circuits/8_to_3_encoder/eight_to_three_encoder_waveform.vcd
$date
	Mon Apr 01 11:57:54 2024
$end
$version
	Icarus Verilog
$end
$timescale
	1s
$end
$scope module eight_to_three_encoder_testbench $end
$var wire 3 ! dout [2:0] $end
$var reg 8 " din [7:0] $end
$scope module dut $end
$var wire 8 # din [7:0] $end
$var reg 3 $ dout [2:0] $end
$upscope $end
$upscope $end
$enddefinitions $end
#0
$dumpvars
bx $
bx #
bx "
bx !
$end
#100
b0 !
b0 $
b10000000 "
b10000000 #
#200
b1 !
b1 $
b1000000 "
b1000000 #
#300
b10 !
b10 $
b100000 "
b100000 #
#400
b11 !
b11 $
b10000 "
b10000 #
#500
b100 !
b100 $
b1000 "
b1000 #
#600
b101 !
b101 $
b100 "
b100 #
#700
b110 !
b110 $
b10 "
b10 #
#800
b111 !
b111 $
b1 "
b1 #
