Combinational_Circuits/Half_Subtractor/half_subtractor.v
module half_subtractor(a,b,diff,borrow);
input a,b;
output diff, borrow;
assign diff=a ^ ~b;
assign borrow=a & ~b;
endmodule

Combinational_Circuits/Full Subtractor/full_subtractor.v
`include "half_subtractor.v"
module full_subtractor(
    input a,b,cin,
    output diff,borrow);
wire d,b1,b2;
half_subtractor hs0(a,b,d,b1);
half_subtractor hs1(d,cin,diff,b2);
assign borrow = b1 | b2;  
endmodule

Combinational_Circuits/Full Subtractor/full_subtractor_tb.v
`include "full_subtractor.v"
module full_subtractor_tb;
reg a,b,cin;
wire diff, borrow;

full_subtractor dut(a,b,cin,diff,borrow);

initial begin
    $dumpfile("full_subtractor_waveform.vcd");
    $dumpvars(0,full_subtractor_tb);
a = 0; b = 0; cin = 0;
#10
a = 0; b = 0; cin = 1;
#10
a = 0; b = 1; cin = 0;
#10
a = 0; b = 1; cin = 1;
#10
a = 1; b = 0; cin = 0;
#10
a = 1; b = 0; cin = 1;
#10
a = 1; b = 1; cin = 0;
#10
a = 1; b = 1; cin = 1;
#10
$finish();
end
endmodule

Combinational_Circuits/Full Subtractor/full_subtractor_waveform.vcd
$date
	Sat Mar 09 18:49:26 2024
$end
$version
	Icarus Verilog
$end
$timescale
	1s
$end
$scope module full_subtractor_tb $end
$var wire 1 ! diff $end
$var wire 1 " borrow $end
$var reg 1 # a $end
$var reg 1 $ b $end
$var reg 1 % cin $end
$scope module dut $end
$var wire 1 # a $end
$var wire 1 $ b $end
$var wire 1 " borrow $end
$var wire 1 % cin $end
$var wire 1 ! diff $end
$var wire 1 & d $end
$var wire 1 ' b2 $end
$var wire 1 ( b1 $end
$scope module hs0 $end
$var wire 1 # a $end
$var wire 1 $ b $end
$var wire 1 ( borrow $end
$var wire 1 & diff $end
$upscope $end
$scope module hs1 $end
$var wire 1 & a $end
$var wire 1 % b $end
$var wire 1 ' borrow $end
$var wire 1 ! diff $end
$upscope $end
$upscope $end
$upscope $end
$enddefinitions $end
#0
$dumpvars
0(
1'
1&
0%
0$
0#
1"
0!
$end
#10
0"
1!
0'
1%
#20
0&
0%
1$
#30
0!
1%
#40
1!
1"
1(
0'
0&
0%
0$
1#
#50
0!
1%
#60
1'
1&
0(
0%
1$
#70
0"
1!
0'
1%
