Combinational_Circuits/Full Adder/half_adder.v
module half_adder(
    input a,b,
    output sum,carry
);
assign sum=a ^ b;
assign carry= a & b;
endmodule

Combinational_Circuits/Full Adder/full_adder.v
//Full adder using half adder
`include "half_adder.v"
module full_adder(
    input a,b,cin,
    output sum,carry
);

wire c,c1,s;

half_adder ha0(a,b,s,c);
half_adder ha1(cin,s,sum,c1);

assign carry = c | c1 ;

endmodule

Combinational_Circuits/Full Adder/full_adder_tb.v
`include "full_adder.v"
module full_adder_tb;
reg a,b,cin;
wire sum,carry;

full_adder dut(a,b,cin,sum,carry);


initial begin
$dumpfile("full_adder_tb.vcd");
$dumpvars(0,full_adder_tb);
a = 0; b = 0; cin = 0;
#10
a = 0; b = 0; cin = 1;
#10
a = 0; b = 1; cin = 0;
#10
a = 0; b = 1; cin = 1;
#10
a = 1; b = 0; cin = 0;
#10
a = 1; b = 0; cin = 1;
#10
a = 1; b = 1; cin = 0;
#10
a = 1; b = 1; cin = 1;
#10
$finish();
end
                
endmodule

Combinational_Circuits/Full Adder/full_adder_tb.vcd
$date
	Sat Mar 09 10:49:09 2024
$end
$version
	Icarus Verilog
$end
$timescale
	1s
$end
$scope module full_adder_tb $end
$var wire 1 ! sum $end
$var wire 1 " carry $end
$var reg 1 # a $end
$var reg 1 $ b $end
$var reg 1 % cin $end
$scope module dut $end
$var wire 1 # a $end
$var wire 1 $ b $end
$var wire 1 " carry $end
$var wire 1 % cin $end
$var wire 1 ! sum $end
$var wire 1 & s $end
$var wire 1 ' c1 $end
$var wire 1 ( c $end
$scope module ha0 $end
$var wire 1 # a $end
$var wire 1 $ b $end
$var wire 1 ( carry $end
$var wire 1 & sum $end
$upscope $end
$scope module ha1 $end
$var wire 1 % a $end
$var wire 1 & b $end
$var wire 1 ' carry $end
$var wire 1 ! sum $end
$upscope $end
$upscope $end
$upscope $end
$enddefinitions $end
#0
$dumpvars
0(
0'
0&
0%
0$
0#
0"
0!
$end
#10
1!
1%
#20
1&
0%
1$
#30
1"
0!
1'
1%
#40
0"
1!
0'
0%
0$
1#
#50
1"
0!
1'
1%
#60
0'
0&
1(
0%
1$
#70
1!
1%
