Combinational_Circuits/4_to_1_Multiplexer/mux_21.v
module mux_21(
    input wire a,b,s,
    output reg y);
always @(*) begin
    if(s)
       assign y=b;
    else 
        assign y=a;    
end

endmodule

Combinational_Circuits/2_to_1_Multiplexer/mux_21_tb.v
`include "mux_21.v"
module mux_21_tb;
    reg a, b, s;
    wire y;
    mux_21 dut(a, b, s, y);
    initial begin
        $dumpfile("mux_21_waveform.vcd");
        $dumpvars(0, mux_21_tb);

        // Test cases
        #10 a=0; b=0; s=0;
        #10 a=0; b=1; s=0;
        #10 a=1; b=0; s=1;
        #10 a=1; b=1; s=1;
        #10 $finish;
    end

    always #5 s = ~s;

    always @(posedge s) begin
        $display("At time = %t, output = %d", $time, y);
    end
endmodule

Combinational_Circuits/2_to_1_Multiplexer/mux_21_waveform.vcd
$date
	Sat Mar 30 11:59:21 2024
$end
$version
	Icarus Verilog
$end
$timescale
	1s
$end
$scope module mux_21_tb $end
$var wire 1 ! y $end
$var reg 1 " a $end
$var reg 1 # b $end
$var reg 1 $ s $end
$scope module dut $end
$var wire 1 " a $end
$var wire 1 # b $end
$var wire 1 $ s $end
$var reg 1 ! y $end
$upscope $end
$upscope $end
$enddefinitions $end
#0
$dumpvars
x$
x#
x"
x!
$end
#10
0!
1$
0#
0"
#15
0$
#20
1!
1$
1#
#25
0!
0$
#30
0$
0#
1!
1"
#35
0!
1$
#40
0$
1!
1#
#45
1$
#50
0$
