Combinational_Circuits/2_to_4_decoder/two_to_four_decoder.v
module two_to_four_decoder(en,a0,a1,d0,d1,d2,d3);
input a0,a1,en;
output d0,d1,d2,d3;

assign d0 = (~a0)& (~a1) & en;
assign d1 = (~a0)& (a1)  & en;
assign d2 = (a0)& (~a1)  & en;
assign d3 = (a0)& (a1)   & en;

endmodule

Combinational_Circuits/3_to_8_decoder/three_to_eigth_decoder.v
`include "two_to_four_decoder.v"
module three_to_eight_decoder(
input enable,a0,a1,a2,
output d0,d1,d2,d3,d4,d5,d6,d7);

wire a2 = (~enable);

two_to_four_decoder dec1(enable,a0,a1,d0,d1,d2,d3);
two_to_four_decoder dec2(a2,a0,a1,d4,d5,d6,d7);

endmodule

Combinational_Circuits/3_to_8_decoder/three_to_eigth_decoder_testbench.v
`include "three_to_eigth_decoder.v"
module three_to_eight_decoder_testbench();
reg  enable,a0,a1,a2;
wire d0,d1,d2,d3,d4,d5,d6,d7;
 
initial begin
    $dumpfile("three_to_eight_decoder_waveform.vcd");
    $dumpvars(0,three_to_eight_decoder_testbench);
end

three_to_eight_decoder dut(enable,a0,a1,a2,d0,d1,d2,d3,d4,d5,d6,d7);

initial begin
$monitor("en=%b, a0=%b, a1=%b,a2=%b , d0=%b,d1=%b,d2=%b,d3=%b,d4=%b,d5=%b,d6=%b,d7=%b",enable,a0,a1,a2,d0,d1,d2,d3,d4,d5,d6,d7);
end

initial begin 
enable=0;
#10 a0=0;a1=0;//000
#10 a0=0;a1=1;//001
#10 a0=1;a1=0;//010
#10 a0=1;a1=1;//011
enable=1;
#10 a0=0;a1=0;//100
#10 a0=0;a1=1;//101
#10 a0=1;a1=0;//110
#10 a0=1;a1=1;//111

end

initial begin 
#90; $finish;
end
endmodule

Combinational_Circuits/3_to_8_decoder/three_to_eight_decoder_waveform.vcd
$date
	Tue Apr 02 21:33:48 2024
$end
$version
	Icarus Verilog
$end
$timescale
	1s
$end
$scope module three_to_eight_decoder_testbench $end
$var wire 1 ! d7 $end
$var wire 1 " d6 $end
$var wire 1 # d5 $end
$var wire 1 $ d4 $end
$var wire 1 % d3 $end
$var wire 1 & d2 $end
$var wire 1 ' d1 $end
$var wire 1 ( d0 $end
$var reg 1 ) a0 $end
$var reg 1 * a1 $end
$var reg 1 + a2 $end
$var reg 1 , enable $end
$scope module dut $end
$var wire 1 ) a0 $end
$var wire 1 * a1 $end
$var wire 1 - a2 $end
$var wire 1 , enable $end
$var wire 1 ! d7 $end
$var wire 1 " d6 $end
$var wire 1 # d5 $end
$var wire 1 $ d4 $end
$var wire 1 % d3 $end
$var wire 1 & d2 $end
$var wire 1 ' d1 $end
$var wire 1 ( d0 $end
$scope module dec1 $end
$var wire 1 ) a0 $end
$var wire 1 * a1 $end
$var wire 1 ( d0 $end
$var wire 1 ' d1 $end
$var wire 1 & d2 $end
$var wire 1 % d3 $end
$var wire 1 , en $end
$upscope $end
$scope module dec2 $end
$var wire 1 ) a0 $end
$var wire 1 * a1 $end
$var wire 1 $ d0 $end
$var wire 1 # d1 $end
$var wire 1 " d2 $end
$var wire 1 ! d3 $end
$var wire 1 - en $end
$upscope $end
$upscope $end
$upscope $end
$enddefinitions $end
#0
$dumpvars
x-
0,
x+
x*
x)
0(
0'
0&
0%
x$
x#
x"
x!
$end
#10
0#
0"
0!
0*
0)
#20
0$
x#
1*
#30
x"
0#
0*
1)
#40
0"
x!
0&
1%
1,
1*
#50
1(
x$
0%
0!
0*
0)
#60
0(
0$
1'
x#
1*
#70
1&
x"
0'
0#
0*
1)
#80
0&
0"
1%
x!
1*
